{
  "annotations": {
    "list": [
      {
        "builtIn": 1,
        "datasource": {
          "type": "grafana",
          "uid": "-- Grafana --"
        },
        "enable": true,
        "hide": true,
        "iconColor": "rgba(0, 211, 255, 1)",
        "name": "Annotations & Alerts",
        "type": "dashboard"
      }
    ]
  },
  "editable": true,
  "fiscalYearStartMonth": 0,
  "graphTooltip": 0,
  "id": 49,
  "links": [],
  "panels": [
    {
      "datasource": {
        "type": "vertamedia-clickhouse-datasource",
        "uid": "P7E099F39B84EA795"
      },
      "description": "reproduce https://github.com/Altinity/clickhouse-grafana/issues/450",
      "fieldConfig": {
        "defaults": {
          "color": {
            "mode": "thresholds"
          },
          "custom": {
            "align": "auto",
            "cellOptions": {
              "type": "auto"
            },
            "inspect": false
          },
          "mappings": [],
          "thresholds": {
            "mode": "absolute",
            "steps": [
              {
                "color": "green",
                "value": null
              },
              {
                "color": "red",
                "value": 80
              }
            ]
          }
        },
        "overrides": []
      },
      "gridPos": {
        "h": 8,
        "w": 12,
        "x": 0,
        "y": 0
      },
      "id": 1,
      "options": {
        "cellHeight": "sm",
        "footer": {
          "countRows": false,
          "fields": "",
          "reducer": [
            "sum"
          ],
          "show": false
        },
        "showHeader": true
      },
      "pluginVersion": "11.4.0",
      "targets": [
        {
          "adHocFilters": [],
          "adHocValuesQuery": "",
          "add_metadata": true,
          "contextWindowSize": "10",
          "database": "default",
          "datasource": {
            "type": "vertamedia-clickhouse-datasource",
            "uid": "P7E099F39B84EA795"
          },
          "dateTimeColDataType": "t",
          "dateTimeType": "DATETIME64",
          "editorMode": "sql",
          "extrapolate": true,
          "format": "table",
          "interval": "",
          "intervalFactor": 1,
          "query": "SELECT t AS t_server_tz, timezone() AS server_timezone, toDateTime(t, 'Asia/Yekaterinburg') AS t_gmt_plus_5, toTypeName(t_gmt_plus_5), value FROM $table",
          "rawQuery": "/* grafana dashboard=New dashboard, user=0 */\nSELECT t AS t_server_tz, toDateTime(t, 'Asia/Yekaterinburg') AS t_gmt_plus_, value FROM default.test_timestamp_formats",
          "refId": "A",
          "round": "0s",
          "skip_comments": true,
          "table": "test_timestamp_formats",
          "useWindowFuncForMacros": true
        }
      ],
      "title": "Table with DateTime columns with server timezone",
      "type": "table"
    }
  ],
  "preload": false,
  "schemaVersion": 40,
  "tags": [],
  "templating": {
    "list": []
  },
  "time": {
    "from": "now-6h",
    "to": "now"
  },
  "timepicker": {},
  "timezone": "browser",
  "title": "Table with DateTime in Server TimeZone",
  "uid": "issue_450",
  "version": 3,
  "weekStart": ""
}
